{
    "id": "0864c2a9-50e3-439b-a86b-d9b3bd713992",
    "title": "Imposto de Renda em 2025: O que Você Precisa Saber sobre as Mudanças e Como Declarar Corretamente",
    "excerpt": "O ano de 2025 se aproxima com possíveis novas regras para o Imposto de Renda. Entenda o que pode mudar na isenção para salários, quais são as expectativas para a nova tabela e as obrigações específicas para o MEI se preparar.",
    "firstPublishedDate": "2025-08-21T00:54:28.079Z",
    "lastPublishedDate": "2025-08-21T22:54:19.423Z",
    "slug": "imposto-de-renda-em-2025-o-que-você-precisa-saber-sobre-as-mudanças-e-como-declarar-corretamente",
    "featured": false,
    "pinned": false,
    "categoryIds": [
        "9a511b56-e966-40d3-8004-9ba88f7fc5f7"
    ],
    "coverMedia": {
        "enabled": true,
        "image": {
            "id": "8ef77a_07bc8269952c42048e7a2ac285b6a59d~mv2.png",
            "url": "https://static.wixstatic.com/media/8ef77a_07bc8269952c42048e7a2ac285b6a59d~mv2.png",
            "height": 720,
            "width": 1280,
            "altText": "Homem com expressão preocupada pensando nas mudanças urgentes do Imposto de Renda 2025, com a imagem de um leão ao fundo.",
            "filename": "thumb-imposto-de-renda-2025-video-janeiro-25.png"
        },
        "displayed": true,
        "custom": true,
        "altText": "Homem com expressão preocupada pensando nas mudanças urgentes do Imposto de Renda 2025, com a imagem de um leão ao fundo."
    },
    "memberId": "32a5c54a-18eb-4691-8a18-8856997a371e",
    "hashtags": [],
    "commentingEnabled": true,
    "minutesToRead": 4,
    "tagIds": [
        "02353134-56fb-428b-bd95-177df7067199",
        "8e4825ba-4408-4870-a99e-31aef646bb77",
        "375e0b0d-8592-4564-ad31-ca36e572af6a",
        "a2475996-9e67-435c-9dfc-c733f6167b05",
        "4e7a57c6-194a-452b-b308-3b7cf7e94b5d",
        "4cbd5326-fbc9-4a64-83ec-6fb6edd928d6",
        "d22de274-a82b-4bf3-862b-cd5ddc24ec72",
        "6ba33a6b-72f5-42ee-a07e-1cf904b0a771",
        "09044587-1fcf-4a05-8f3d-50c710f4bdaf",
        "f140d0eb-1c63-4de3-bab9-ed07d5539586",
        "d4f76189-b1fd-4fc2-a170-21998964fea2",
        "d4364121-cb32-4ef5-b436-517ea6c869de",
        "acdddc28-4c6d-4c78-b466-bf32e54851cf",
        "5b81fcf6-75cd-4ca8-b771-fe0c77a3b21b",
        "07c6fb53-fa40-420b-a1c3-8d4384378f71",
        "97c8e4c0-d32f-473c-804c-b028c099fa8a",
        "84d61950-5034-46c0-9daa-7a6b14c8df30"
    ],
    "relatedPostIds": [],
    "pricingPlanIds": [],
    "language": "pt",
    "preview": false,
    "contentId": "68a7a39b6c4f5bcba97caaa9",
    "mostRecentContributorId": "8ef77acd-64b1-45e0-819e-bc51664090c5",
    "media": {
        "wixMedia": {
            "image": {
                "id": "8ef77a_07bc8269952c42048e7a2ac285b6a59d~mv2.png",
                "url": "https://static.wixstatic.com/media/8ef77a_07bc8269952c42048e7a2ac285b6a59d~mv2.png",
                "height": 720,
                "width": 1280,
                "altText": "Homem com expressão preocupada pensando nas mudanças urgentes do Imposto de Renda 2025, com a imagem de um leão ao fundo.",
                "filename": "thumb-imposto-de-renda-2025-video-janeiro-25.png"
            }
        },
        "displayed": true,
        "custom": true,
        "altText": "Homem com expressão preocupada pensando nas mudanças urgentes do Imposto de Renda 2025, com a imagem de um leão ao fundo."
    },
    "hasUnpublishedChanges": false,
    "translations": [],
    "customExcerpt": true,
    "internalCategoryIds": [],
    "internalRelatedPostIds": [],
    "richContent": {
        "nodes": [
            {
                "type": "PARAGRAPH",
                "id": "klmdp30730",
                "nodes": [
                    {
                        "type": "TEXT",
                        "id": "",
                        "nodes": [],
                        "textData": {
                            "text": "O ano de 2025 está se aproximando, e com ele vêm algumas mudanças nas regras do Imposto de Renda, especialmente para quem recebe até R$ 5.000 mensais, além de novos desafios para os microempreendedores individuais (MEI). Neste artigo, vamos explicar o que muda em relação ao Imposto de Renda para o próximo ano, esclarecer mitos, e dar dicas sobre como fazer a declaração corretamente.\n",
                            "decorations": []
                        }
                    }
                ],
                "style": {
                    "paddingBottom": "2px"
                },
                "paragraphData": {
                    "textStyle": {
                        "textAlignment": "JUSTIFY"
                    }
                }
            },
            {
                "type": "HEADING",
                "id": "biqri30732",
                "nodes": [
                    {
                        "type": "TEXT",
                        "id": "",
                        "nodes": [],
                        "textData": {
                            "text": "Para te ajudar a entender melhor, separamos um vídeo. Assista:",
                            "decorations": [
                                {
                                    "type": "ITALIC",
                                    "italicData": true
                                }
                            ]
                        }
                    }
                ],
                "style": {
                    "paddingBottom": "2px"
                },
                "headingData": {
                    "level": 4,
                    "textStyle": {
                        "textAlignment": "JUSTIFY"
                    }
                }
            },
            {
                "type": "PARAGRAPH",
                "id": "18imt30734",
                "nodes": [
                    {
                        "type": "TEXT",
                        "id": "",
                        "nodes": [],
                        "textData": {
                            "text": "     ",
                            "decorations": []
                        }
                    }
                ],
                "style": {
                    "paddingBottom": "2px"
                },
                "paragraphData": {
                    "textStyle": {
                        "textAlignment": "JUSTIFY"
                    }
                }
            },
            {
                "type": "VIDEO",
                "id": "v4x7w30994",
                "nodes": [],
                "videoData": {
                    "containerData": {
                        "width": {
                            "size": "CONTENT"
                        },
                        "alignment": "CENTER",
                        "textWrap": true
                    },
                    "video": {
                        "src": {
                            "url": "https://www.youtube.com/watch?v=TZLpKNEXFbM"
                        },
                        "duration": 441
                    },
                    "thumbnail": {
                        "src": {
                            "url": "https://i.ytimg.com/vi/TZLpKNEXFbM/maxresdefault.jpg"
                        },
                        "width": 1280,
                        "height": 720
                    },
                    "title": "IMPOSTO DE RENDA (IRPF) 2025 - VEJA TODAS AS MUDANÇAS"
                }
            },
            {
                "type": "HEADING",
                "id": "spi7i30736",
                "nodes": [
                    {
                        "type": "TEXT",
                        "id": "",
                        "nodes": [],
                        "textData": {
                            "text": "1. ",
                            "decorations": [
                                {
                                    "type": "ITALIC",
                                    "italicData": true
                                }
                            ]
                        }
                    },
                    {
                        "type": "TEXT",
                        "id": "",
                        "nodes": [],
                        "textData": {
                            "text": "A Isenção de Imposto de Renda para Salários de até R$ 5.000",
                            "decorations": [
                                {
                                    "type": "BOLD",
                                    "fontWeightValue": 700
                                },
                                {
                                    "type": "ITALIC",
                                    "italicData": true
                                }
                            ]
                        }
                    }
                ],
                "style": {
                    "paddingBottom": "2px"
                },
                "headingData": {
                    "level": 4,
                    "textStyle": {
                        "textAlignment": "JUSTIFY"
                    }
                }
            },
            {
                "type": "PARAGRAPH",
                "id": "vnp6g30739",
                "nodes": [
                    {
                        "type": "TEXT",
                        "id": "",
                        "nodes": [],
                        "textData": {
                            "text": "\nO governo tem falado bastante sobre isenção de Imposto de Renda para quem recebe até R$ 5.000 por mês. No entanto, é importante destacar que, apesar da promessa do presidente Lula de que a isenção seria válida para 2024 e 2025, essa mudança ainda não é certa. A tabela de 2025 ainda não foi oficialmente publicada e, por enquanto, não há garantias de que o valor de R$ 5.000 esteja contemplado nas faixas de isenção. A expectativa é de que uma tabela diferenciada seja implementada, mas isso dependerá de decisões políticas e de aprovação no Congresso.\n",
                            "decorations": []
                        }
                    }
                ],
                "style": {
                    "paddingBottom": "2px"
                },
                "paragraphData": {
                    "textStyle": {
                        "textAlignment": "JUSTIFY"
                    }
                }
            },
            {
                "type": "HEADING",
                "id": "bmfj830741",
                "nodes": [
                    {
                        "type": "TEXT",
                        "id": "",
                        "nodes": [],
                        "textData": {
                            "text": "2. ",
                            "decorations": [
                                {
                                    "type": "ITALIC",
                                    "italicData": true
                                }
                            ]
                        }
                    },
                    {
                        "type": "TEXT",
                        "id": "",
                        "nodes": [],
                        "textData": {
                            "text": "A Tabela de Imposto de Renda de 2025",
                            "decorations": [
                                {
                                    "type": "BOLD",
                                    "fontWeightValue": 700
                                },
                                {
                                    "type": "ITALIC",
                                    "italicData": true
                                }
                            ]
                        }
                    }
                ],
                "style": {
                    "paddingBottom": "2px"
                },
                "headingData": {
                    "level": 4,
                    "textStyle": {
                        "textAlignment": "JUSTIFY"
                    }
                }
            },
            {
                "type": "PARAGRAPH",
                "id": "s2zoo30744",
                "nodes": [
                    {
                        "type": "TEXT",
                        "id": "",
                        "nodes": [],
                        "textData": {
                            "text": "\nEmbora não tenha sido oficialmente confirmada, o governo já circulou informações sobre as faixas de renda e alíquotas para o Imposto de Renda em 2025. Em 2024, a tabela apresenta faixas com alíquotas progressivas, começando em 7,5% até chegar a 27,5%. Para 2025, espera-se que a faixa de isenção seja até R$ 2.259, com alíquotas a partir de 7,5%, 15%, 22%, chegando à máxima de 27,5% para quem ultrapassar os R$ 5.000 mensais.\n",
                            "decorations": []
                        }
                    }
                ],
                "style": {
                    "paddingBottom": "2px"
                },
                "paragraphData": {
                    "textStyle": {
                        "textAlignment": "JUSTIFY"
                    }
                }
            },
            {
                "type": "HEADING",
                "id": "nul3t30746",
                "nodes": [
                    {
                        "type": "TEXT",
                        "id": "",
                        "nodes": [],
                        "textData": {
                            "text": "3. ",
                            "decorations": [
                                {
                                    "type": "ITALIC",
                                    "italicData": true
                                }
                            ]
                        }
                    },
                    {
                        "type": "TEXT",
                        "id": "",
                        "nodes": [],
                        "textData": {
                            "text": "Declaração de Imposto de Renda: O Que Você Precisa Saber",
                            "decorations": [
                                {
                                    "type": "BOLD",
                                    "fontWeightValue": 700
                                },
                                {
                                    "type": "ITALIC",
                                    "italicData": true
                                }
                            ]
                        }
                    }
                ],
                "style": {
                    "paddingBottom": "2px"
                },
                "headingData": {
                    "level": 4,
                    "textStyle": {
                        "textAlignment": "JUSTIFY"
                    }
                }
            },
            {
                "type": "PARAGRAPH",
                "id": "hajf130749",
                "nodes": [
                    {
                        "type": "TEXT",
                        "id": "",
                        "nodes": [],
                        "textData": {
                            "text": "\nA declaração de Imposto de Renda é obrigatória para quem teve uma renda tributável superior a R$ 30.639,99 no ano anterior. Ou seja, se você ganhou mais do que essa quantia durante o ano de 2024, deverá fazer a declaração de 2025. Vale destacar que, mesmo que você não tenha que pagar imposto devido a deduções, a declaração continua sendo obrigatória.\n\nSe você está na faixa de isenção, como mencionado, com renda de até R$ 2.259 mensais, você não pagará o imposto, mas ainda assim deve fazer a declaração para informar ao fisco que não há impostos devidos.\n",
                            "decorations": []
                        }
                    }
                ],
                "style": {
                    "paddingBottom": "2px"
                },
                "paragraphData": {
                    "textStyle": {
                        "textAlignment": "JUSTIFY"
                    }
                }
            },
            {
                "type": "HEADING",
                "id": "0m7ql30751",
                "nodes": [
                    {
                        "type": "TEXT",
                        "id": "",
                        "nodes": [],
                        "textData": {
                            "text": "4. ",
                            "decorations": [
                                {
                                    "type": "ITALIC",
                                    "italicData": true
                                }
                            ]
                        }
                    },
                    {
                        "type": "TEXT",
                        "id": "",
                        "nodes": [],
                        "textData": {
                            "text": "Microempreendedores Individuais (MEI) e Imposto de Renda",
                            "decorations": [
                                {
                                    "type": "BOLD",
                                    "fontWeightValue": 700
                                },
                                {
                                    "type": "ITALIC",
                                    "italicData": true
                                }
                            ]
                        }
                    }
                ],
                "style": {
                    "paddingBottom": "2px"
                },
                "headingData": {
                    "level": 4,
                    "textStyle": {
                        "textAlignment": "JUSTIFY"
                    }
                }
            },
            {
                "type": "PARAGRAPH",
                "id": "5sgbe30754",
                "nodes": [
                    {
                        "type": "TEXT",
                        "id": "",
                        "nodes": [],
                        "textData": {
                            "text": "\nOs microempreendedores individuais (MEI) têm um tratamento tributário específico quando se trata de Imposto de Renda. O MEI não precisa fazer a declaração anual de Imposto de Renda, mas deve preencher a Declaração Anual do Simples Nacional (DASN), que é obrigatória, independentemente do faturamento.\n\nAlém disso, o MEI deve manter controle rigoroso de suas vendas e receitas. Para quem tem dificuldades na organização, ferramentas como o ",
                            "decorations": []
                        }
                    },
                    {
                        "type": "TEXT",
                        "id": "",
                        "nodes": [],
                        "textData": {
                            "text": "EasyGestor",
                            "decorations": [
                                {
                                    "type": "BOLD",
                                    "fontWeightValue": 700
                                },
                                {
                                    "type": "LINK",
                                    "linkData": {}
                                }
                            ]
                        }
                    },
                    {
                        "type": "TEXT",
                        "id": "",
                        "nodes": [],
                        "textData": {
                            "text": "podem ajudar na gestão do negócio, facilitando a emissão de notas fiscais e o acompanhamento do faturamento. Isso é essencial para garantir que o MEI esteja cumprindo com todas as suas obrigações tributárias e evitando problemas com a Receita Federal.\n",
                            "decorations": []
                        }
                    }
                ],
                "style": {
                    "paddingBottom": "2px"
                },
                "paragraphData": {
                    "textStyle": {
                        "textAlignment": "JUSTIFY"
                    }
                }
            },
            {
                "type": "HEADING",
                "id": "o11hs30758",
                "nodes": [
                    {
                        "type": "TEXT",
                        "id": "",
                        "nodes": [],
                        "textData": {
                            "text": "Faça o controle financeiro da sua empresa com Easygestor e ganhe notas grátis!",
                            "decorations": [
                                {
                                    "type": "LINK",
                                    "linkData": {}
                                }
                            ]
                        }
                    }
                ],
                "style": {
                    "paddingBottom": "2px"
                },
                "headingData": {
                    "level": 4,
                    "textStyle": {
                        "textAlignment": "JUSTIFY"
                    }
                }
            },
            {
                "type": "HEADING",
                "id": "jx8fo30760",
                "nodes": [
                    {
                        "type": "TEXT",
                        "id": "",
                        "nodes": [],
                        "textData": {
                            "text": "5. ",
                            "decorations": [
                                {
                                    "type": "ITALIC",
                                    "italicData": true
                                }
                            ]
                        }
                    },
                    {
                        "type": "TEXT",
                        "id": "",
                        "nodes": [],
                        "textData": {
                            "text": "A Diferença Entre Declarar e Pagar Imposto",
                            "decorations": [
                                {
                                    "type": "BOLD",
                                    "fontWeightValue": 700
                                },
                                {
                                    "type": "ITALIC",
                                    "italicData": true
                                }
                            ]
                        }
                    }
                ],
                "style": {
                    "paddingBottom": "2px"
                },
                "headingData": {
                    "level": 4,
                    "textStyle": {
                        "textAlignment": "JUSTIFY"
                    }
                }
            },
            {
                "type": "PARAGRAPH",
                "id": "jr94l30763",
                "nodes": [
                    {
                        "type": "TEXT",
                        "id": "",
                        "nodes": [],
                        "textData": {
                            "text": "\nMuitas pessoas confundem a declaração de Imposto de Renda com o pagamento efetivo do imposto. É importante entender que, em algumas situações, você pode ser obrigado a declarar, mas não pagar imposto, ou vice-versa. A declaração de Imposto de Renda envolve informar todos os rendimentos, enquanto o pagamento do imposto ocorre apenas se a sua renda tributável ultrapassar as faixas determinadas pela tabela.\n\nSe você estiver em uma faixa onde precisa pagar, o valor será calculado com base na tabela progressiva. Já se a sua faixa de rendimentos não ultrapassar o limite de isenção, você não pagará o imposto, mas deverá informar à Receita Federal.\n",
                            "decorations": []
                        }
                    }
                ],
                "style": {
                    "paddingBottom": "2px"
                },
                "paragraphData": {
                    "textStyle": {
                        "textAlignment": "JUSTIFY"
                    }
                }
            },
            {
                "type": "HEADING",
                "id": "o7qtd30765",
                "nodes": [
                    {
                        "type": "TEXT",
                        "id": "",
                        "nodes": [],
                        "textData": {
                            "text": "6. ",
                            "decorations": [
                                {
                                    "type": "ITALIC",
                                    "italicData": true
                                }
                            ]
                        }
                    },
                    {
                        "type": "TEXT",
                        "id": "",
                        "nodes": [],
                        "textData": {
                            "text": "A Tabela de Imposto de Renda no Site da Receita Federal",
                            "decorations": [
                                {
                                    "type": "BOLD",
                                    "fontWeightValue": 700
                                },
                                {
                                    "type": "ITALIC",
                                    "italicData": true
                                }
                            ]
                        }
                    }
                ],
                "style": {
                    "paddingBottom": "2px"
                },
                "headingData": {
                    "level": 4,
                    "textStyle": {
                        "textAlignment": "JUSTIFY"
                    }
                }
            },
            {
                "type": "PARAGRAPH",
                "id": "xqpes30768",
                "nodes": [
                    {
                        "type": "TEXT",
                        "id": "",
                        "nodes": [],
                        "textData": {
                            "text": "\nA Receita Federal mantém uma tabela atualizada em seu site para consulta pública, onde é possível verificar as faixas de renda e as alíquotas que devem ser aplicadas. No entanto, o governo ainda não publicou a tabela de 2025, e a tabela de 2024 pode sofrer alterações após as discussões no Congresso.\n\nÉ importante que os contribuintes fiquem atentos às atualizações e consultem o site da Receita Federal para informações precisas. A tabela de 2024, que já está disponível no site da Receita, pode ser útil como base até que a oficial de 2025 seja publicada.\n",
                            "decorations": []
                        }
                    }
                ],
                "style": {
                    "paddingBottom": "2px"
                },
                "paragraphData": {
                    "textStyle": {
                        "textAlignment": "JUSTIFY"
                    }
                }
            },
            {
                "type": "HEADING",
                "id": "d9kn330770",
                "nodes": [
                    {
                        "type": "TEXT",
                        "id": "",
                        "nodes": [],
                        "textData": {
                            "text": "7.",
                            "decorations": [
                                {
                                    "type": "ITALIC",
                                    "italicData": true
                                }
                            ]
                        }
                    },
                    {
                        "type": "TEXT",
                        "id": "",
                        "nodes": [],
                        "textData": {
                            "text": " A Necessidade de Acompanhamento e Planejamento",
                            "decorations": [
                                {
                                    "type": "BOLD",
                                    "fontWeightValue": 700
                                },
                                {
                                    "type": "ITALIC",
                                    "italicData": true
                                }
                            ]
                        }
                    }
                ],
                "style": {
                    "paddingBottom": "2px"
                },
                "headingData": {
                    "level": 4,
                    "textStyle": {
                        "textAlignment": "JUSTIFY"
                    }
                }
            },
            {
                "type": "PARAGRAPH",
                "id": "bqzvp30773",
                "nodes": [
                    {
                        "type": "TEXT",
                        "id": "",
                        "nodes": [],
                        "textData": {
                            "text": "\nO Imposto de Renda é um tema complexo, mas essencial para a organização financeira tanto de pessoas físicas quanto de empresas. Ficar atento às mudanças na legislação e se planejar corretamente é fundamental para evitar surpresas na hora de declarar e pagar os impostos devidos.\n\nSe você ainda tem dúvidas sobre como fazer a declaração ou precisa de ajuda com o controle da sua empresa, é recomendado consultar um contador especializado. E, claro, continue acompanhando os vídeos e conteúdos do canal, onde estamos sempre trazendo atualizações importantes sobre impostos, empreendedorismo e finanças.\n\nSe você gostou deste conteúdo, não se esqueça de curtir e compartilhar. Fique atento às novas publicações e boas práticas fiscais para 2025!",
                            "decorations": []
                        }
                    }
                ],
                "style": {
                    "paddingBottom": "2px"
                },
                "paragraphData": {
                    "textStyle": {
                        "textAlignment": "JUSTIFY"
                    }
                }
            }
        ],
        "documentStyle": {}
    }
}